micropipenv.py
micropipenv-1.10.0.dist-info/licenses/LICENSE
micropipenv-1.10.0.dist-info/METADATA
micropipenv-1.10.0.dist-info/WHEEL
micropipenv-1.10.0.dist-info/entry_points.txt
micropipenv-1.10.0.dist-info/top_level.txt
micropipenv-1.10.0.dist-info/RECORD
