Metadata-Version: 2.4
Name: micropipenv
Version: 1.10.0
Summary: A simple wrapper around pip to support requirements.txt, Pipenv and Poetry files for containerized applications
Home-page: https://github.com/thoth-station/micropipenv
Download-URL: https://pypi.org/project/micropipenv
Author: Fridolin Pokorny
Author-email: fridex.devel@gmail.com
Maintainer: Fridolin Pokorny
Maintainer-email: fridex.devel@gmail.com
License: LGPLv3+
Keywords: packaging,pipenv,poetry,pip,dependencies,dependency-management,utilities
Classifier: Development Status :: 5 - Production/Stable
Classifier: Intended Audience :: Developers
Classifier: License :: OSI Approved :: GNU Lesser General Public License v3 or later (LGPLv3+)
Classifier: Programming Language :: Python
Classifier: Programming Language :: Python :: 3.6
Classifier: Programming Language :: Python :: 3.9
Classifier: Programming Language :: Python :: 3.10
Classifier: Programming Language :: Python :: 3.11
Classifier: Programming Language :: Python :: 3.12
Classifier: Programming Language :: Python :: 3.13
Classifier: Programming Language :: Python :: 3.14
Classifier: Programming Language :: Python :: Implementation :: CPython
License-File: LICENSE
Requires-Dist: pip>=9
Provides-Extra: toml
Requires-Dist: toml; python_version < "3.11" and extra == "toml"
Provides-Extra: tests
Requires-Dist: flexmock; extra == "tests"
Requires-Dist: pytest; extra == "tests"
Requires-Dist: pytest-timeout; extra == "tests"
Requires-Dist: pytest-venv>=0.3; extra == "tests"
Requires-Dist: packaging; extra == "tests"
Dynamic: download-url
Dynamic: license-file
